cf_dns_edit/__about__.py
cf_dns_edit/__init__.py
cf_dns_edit/main.py
cf_dns_edit/tcss/about.tcss
cf_dns_edit/tcss/confirmation.tcss
cf_dns_edit/tcss/dns_management.tcss
cf_dns_edit/tcss/domain_management.tcss
cf_dns_edit/tcss/login.tcss
cf_dns_edit/tcss/main.tcss
cf_dns_edit/tcss/record_management.tcss
cf_dns_edit/tcss/screen_too_small.tcss
cf_dns_edit-0.2.5.dist-info/METADATA
cf_dns_edit-0.2.5.dist-info/WHEEL
cf_dns_edit-0.2.5.dist-info/entry_points.txt
cf_dns_edit-0.2.5.dist-info/licenses/LICENSE
cf_dns_edit-0.2.5.dist-info/RECORD
