Metadata-Version: 2.4
Name: cf-dns-edit
Version: 0.2.5
Summary: TUI to edit DNS records for cloudflare domains
Author-email: ShyMike <122023566+ImShyMike@users.noreply.github.com>
License-File: LICENSE
Requires-Python: >=3.11
Requires-Dist: click>=8.2.1
Requires-Dist: cloudflare>=4.2.0
Requires-Dist: python-dotenv>=1.1.1
Requires-Dist: textual>=3.5.0
